{
  "season": "SHINSEKAI",
  "year": 2026,
  "air_dates": "2026-03-26 to ongoing",
  "debut_group": null,
  "total_trainees": 101,
  "ranking_milestones": [
    {
      "key": "p1",
      "label": "練習生評価",
      "short": "①",
      "official": true
    },
    {
      "key": "p2",
      "label": "グループバトル",
      "short": "②",
      "official": true
    },
    {
      "key": "rc1",
      "label": "第1回順位発表式",
      "short": "RC1",
      "official": true,
      "ceremony": true,
      "episode": 5
    },
    {
      "key": "rc2",
      "label": "第2回順位発表式",
      "short": "RC2",
      "official": true,
      "ceremony": true,
      "episode": 8
    }
  ],
  "ongoing": true,
  "last_updated_episode": "Episode 8 (2026-05-08)",
  "debut_count": 12,
  "image_url_template": "https://produce101.jp/static/produce101audition/profile/env7uixvQmE8yymQYP/profile/{image_id}.jpg",
  "notes": "Voting system: National Producer votes (70%) + SEKAI Producer votes (30%). A separate 'Global Ranker' track exists with inverted weights (30%/70%). Ranks 1-50 reflect the Episode 8 (2nd ranking ceremony) announced positions, where 50 trainees advanced to the next stage. Trainees ranked 51+ (no longer on stage / eliminated by Episode 5 cut) are listed with rank: null. The show is still on air; debut lineup is undetermined.",
  "trainees": [
    {
      "rank": 1,
      "name_jp": "加藤 大樹",
      "name_romaji": "Kato Daiki",
      "stage_name": "K.DAIKI",
      "image_id": "katodaiki",
      "rank_history": {
        "p1": 3,
        "p2": 2,
        "rc1": 1,
        "rc2": 1
      },
      "debuted": false,
      "ongoing_rank": true,
      "level_test": "B",
      "re_evaluation": "A",
      "level_test_team": {
        "song": "SHINE (Japanese ver.)"
      },
      "group_battle": {
        "song": "Energetic",
        "team": "flow1",
        "result": "lose"
      }
    },
    {
      "rank": 2,
      "name_jp": "安部 結蘭",
      "name_romaji": "Abe Yura",
      "stage_name": "YURA",
      "image_id": "abeyura",
      "rank_history": {
        "p1": 4,
        "p2": 4,
        "rc1": 3,
        "rc2": 2
      },
      "debuted": false,
      "ongoing_rank": true,
      "level_test": "C",
      "re_evaluation": "A",
      "level_test_team": {
        "song": "SPECIALZ"
      },
      "group_battle": {
        "song": "Energetic",
        "team": "flow1",
        "result": "lose"
      }
    },
    {
      "rank": 3,
      "name_jp": "照井 康祐",
      "name_romaji": "Terui Kosuke",
      "stage_name": "KOSUKE",
      "image_id": "teruikosuke",
      "rank_history": {
        "p1": 9,
        "p2": 8,
        "rc1": 7,
        "rc2": 3
      },
      "debuted": false,
      "ongoing_rank": true,
      "level_test": "C",
      "re_evaluation": "A",
      "level_test_team": {
        "song": "はじめまして"
      },
      "group_battle": {
        "song": "Love Seeker",
        "team": "Heart Shakers",
        "result": "lose"
      }
    },
    {
      "rank": 4,
      "name_jp": "釼持 吉成",
      "name_romaji": "Kenmotsu Kinari",
      "stage_name": "KINARI",
      "image_id": "kenmotsukinari",
      "rank_history": {
        "p1": 2,
        "p2": 1,
        "rc1": 2,
        "rc2": 4
      },
      "debuted": false,
      "ongoing_rank": true,
      "level_test": "F",
      "re_evaluation": "A",
      "level_test_team": {
        "song": "HOWL"
      },
      "group_battle": {
        "song": "Bite Me -Japanese ver.-",
        "team": "Kiss Me",
        "result": "lose"
      }
    },
    {
      "rank": 5,
      "name_jp": "矢田 佳暉",
      "name_romaji": "Yada Yoshiki",
      "stage_name": "YOSHIKI",
      "image_id": "yadayoshiki",
      "rank_history": {
        "p1": 1,
        "p2": 3,
        "rc1": 4,
        "rc2": 5
      },
      "debuted": false,
      "ongoing_rank": true,
      "level_test": "A",
      "re_evaluation": "B",
      "level_test_team": {
        "song": "WISH (Japanese ver.)"
      },
      "group_battle": {
        "song": "Energetic",
        "team": "flow1",
        "result": "lose"
      }
    },
    {
      "rank": 6,
      "name_jp": "パク・シヨン",
      "name_romaji": "Park Siyoung",
      "stage_name": "SIYOUNG",
      "image_id": "parksiyoung",
      "rank_history": {
        "p1": 5,
        "p2": 5,
        "rc1": 6,
        "rc2": 6
      },
      "debuted": false,
      "ongoing_rank": true,
      "level_test": "A",
      "re_evaluation": "A",
      "group_battle": {
        "song": "Energetic",
        "team": "flow1",
        "result": "lose"
      }
    },
    {
      "rank": 7,
      "name_jp": "オ・シンヘン",
      "name_romaji": "Oh Shinhaeng",
      "stage_name": "SHINHAENG",
      "image_id": "ohshinhaeng",
      "rank_history": {
        "p1": 6,
        "p2": 6,
        "rc1": 5,
        "rc2": 7
      },
      "debuted": false,
      "ongoing_rank": true,
      "level_test": "B",
      "re_evaluation": "A",
      "group_battle": {
        "song": "Bite Me -Japanese ver.-",
        "team": "Kiss Me",
        "result": "lose"
      }
    },
    {
      "rank": 8,
      "name_jp": "飯塚 亮賀",
      "name_romaji": "Iizuka Ryoga",
      "stage_name": "RYOGA",
      "image_id": "iizukaryoga",
      "rank_history": {
        "p1": 10,
        "p2": 11,
        "rc1": 12,
        "rc2": 8
      },
      "debuted": false,
      "ongoing_rank": true,
      "level_test": "C",
      "re_evaluation": "F",
      "level_test_team": {
        "song": "はじめまして"
      },
      "group_battle": {
        "song": "最高到達点",
        "team": "新世海マリーンズ",
        "result": "win"
      }
    },
    {
      "rank": 9,
      "name_jp": "ユ・ヒョンスン",
      "name_romaji": "Yu Hyeonseung",
      "stage_name": "HYEONSEUNG",
      "image_id": "yoohyeonseung",
      "rank_history": {
        "p1": 15,
        "p2": 10,
        "rc1": 8,
        "rc2": 9
      },
      "debuted": false,
      "ongoing_rank": true,
      "level_test": "A",
      "re_evaluation": "A",
      "group_battle": {
        "song": "IRIS OUT",
        "team": "CREEEPY DEVILS",
        "result": "lose"
      }
    },
    {
      "rank": 10,
      "name_jp": "杉山 竜司",
      "name_romaji": "Sugiyama Ryuji",
      "stage_name": "RYUJI",
      "image_id": "sugiyamaryuji",
      "rank_history": {
        "p1": 22,
        "p2": 25,
        "rc1": 23,
        "rc2": 10
      },
      "debuted": false,
      "ongoing_rank": true,
      "level_test": "A",
      "re_evaluation": "B",
      "level_test_team": {
        "song": "WOKE UP"
      },
      "group_battle": {
        "song": "Energetic",
        "team": "TO BE ENERGY",
        "result": "win"
      }
    },
    {
      "rank": 11,
      "name_jp": "柳谷 伊冴",
      "name_romaji": "Yanagiya Issa",
      "stage_name": "ISSA",
      "image_id": "yanagiyaissa",
      "rank_history": {
        "p1": 48,
        "p2": 37,
        "rc1": 19,
        "rc2": 11
      },
      "debuted": false,
      "ongoing_rank": true,
      "level_test": "C",
      "re_evaluation": "C",
      "level_test_team": {
        "song": "SEVENTEEN"
      },
      "group_battle": {
        "song": "Bite Me -Japanese ver.-",
        "team": "虹色Bites",
        "result": "win"
      }
    },
    {
      "rank": 12,
      "name_jp": "土田 央修",
      "name_romaji": "Tsuchida Osuke",
      "stage_name": "OSUKE",
      "image_id": "tsuchidaosuke",
      "rank_history": {
        "p1": 14,
        "p2": 14,
        "rc1": 13,
        "rc2": 12
      },
      "debuted": false,
      "ongoing_rank": true,
      "level_test": "A",
      "re_evaluation": "A",
      "level_test_team": {
        "song": "Butter-Fly"
      },
      "group_battle": {
        "song": "Energetic",
        "team": "TO BE ENERGY",
        "result": "win"
      }
    },
    {
      "rank": 13,
      "name_jp": "チェン・リッキー",
      "name_romaji": "Chen Rickey",
      "stage_name": "RICKEY",
      "image_id": "chenrickey",
      "rank_history": {
        "p1": 38,
        "p2": 28,
        "rc1": 25,
        "rc2": 13
      },
      "debuted": false,
      "ongoing_rank": true,
      "level_test": "C",
      "re_evaluation": "D",
      "level_test_team": {
        "song": "Don't Tell Nobody"
      },
      "group_battle": {
        "song": "唱",
        "team": "GLOBOYS",
        "result": "lose"
      }
    },
    {
      "rank": 14,
      "name_jp": "濱田 永遠",
      "name_romaji": "Hamada Towa",
      "stage_name": "TOWA",
      "image_id": "hamadatowa",
      "rank_history": {
        "p1": 16,
        "p2": 16,
        "rc1": 15,
        "rc2": 14
      },
      "debuted": false,
      "ongoing_rank": true,
      "level_test": "B",
      "re_evaluation": "B",
      "level_test_team": {
        "song": "Gooey"
      },
      "group_battle": {
        "song": "CASE143",
        "team": "上等Kids(♡)",
        "result": "win"
      }
    },
    {
      "rank": 15,
      "name_jp": "熊部 拓斗",
      "name_romaji": "Kumabe Takuto",
      "stage_name": "K.TAKUTO",
      "image_id": "kumabetakuto",
      "rank_history": {
        "p1": 12,
        "p2": 9,
        "rc1": 9,
        "rc2": 15
      },
      "debuted": false,
      "ongoing_rank": true,
      "level_test": "D",
      "re_evaluation": "D",
      "level_test_team": {
        "song": "HOWL"
      },
      "group_battle": {
        "song": "Bite Me -Japanese ver.-",
        "team": "虹色Bites",
        "result": "win"
      }
    },
    {
      "rank": 16,
      "name_jp": "後藤 結",
      "name_romaji": "Goto Yuki",
      "stage_name": "YUKI",
      "image_id": "gotoyuki",
      "rank_history": {
        "p1": 17,
        "p2": 17,
        "rc1": 17,
        "rc2": 16
      },
      "debuted": false,
      "ongoing_rank": true,
      "level_test": "D",
      "re_evaluation": "C",
      "level_test_team": {
        "song": "いいじゃん"
      },
      "group_battle": {
        "song": "Energetic",
        "team": "TO BE ENERGY",
        "result": "win"
      }
    },
    {
      "rank": 17,
      "name_jp": "浅香 孝太郎",
      "name_romaji": "Asaka Kotaro",
      "stage_name": "KOTARO",
      "image_id": "asakakotaro",
      "rank_history": {
        "p1": 26,
        "p2": 24,
        "rc1": 18,
        "rc2": 17
      },
      "debuted": false,
      "ongoing_rank": true,
      "level_test": "D",
      "re_evaluation": "D",
      "level_test_team": {
        "song": "SPECIALZ"
      }
    },
    {
      "rank": 18,
      "name_jp": "小野 慶人",
      "name_romaji": "Ono Keito",
      "stage_name": "KEITO",
      "image_id": "onokeito",
      "rank_history": {
        "p1": 13,
        "p2": 15,
        "rc1": 16,
        "rc2": 18
      },
      "debuted": false,
      "ongoing_rank": true,
      "level_test": "D",
      "re_evaluation": "C",
      "level_test_team": {
        "song": "踊り子"
      },
      "group_battle": {
        "song": "最高到達点",
        "team": "新世海マリーンズ",
        "result": "win"
      }
    },
    {
      "rank": 19,
      "name_jp": "青沼 昂史朗",
      "name_romaji": "Aonuma Koshiro",
      "stage_name": "KOSHIRO",
      "image_id": "aonumakoshiro",
      "rank_history": {
        "p1": 31,
        "p2": 27,
        "rc1": 26,
        "rc2": 19
      },
      "debuted": false,
      "ongoing_rank": true,
      "level_test": "F",
      "re_evaluation": "D",
      "level_test_team": {
        "song": "Rocketeer"
      },
      "group_battle": {
        "song": "最高到達点",
        "team": "新世海マリーンズ",
        "result": "win"
      }
    },
    {
      "rank": 20,
      "name_jp": "小清水 蓮",
      "name_romaji": "Koshimizu Ren",
      "stage_name": "KO.REN",
      "image_id": "koshimizuren",
      "rank_history": {
        "p1": 8,
        "p2": 12,
        "rc1": 14,
        "rc2": 20
      },
      "debuted": false,
      "ongoing_rank": true,
      "level_test": "C",
      "re_evaluation": "F",
      "level_test_team": {
        "song": "Supercali"
      },
      "group_battle": {
        "song": "Bite Me -Japanese ver.-",
        "team": "虹色Bites",
        "result": "win"
      }
    },
    {
      "rank": 21,
      "name_jp": "アダム・ナガイ",
      "name_romaji": "Adam Nagai",
      "stage_name": "ADAM",
      "image_id": "adamnagai",
      "rank_history": {
        "p1": 7,
        "p2": 7,
        "rc1": 10,
        "rc2": 21
      },
      "debuted": false,
      "ongoing_rank": true,
      "level_test": "A",
      "re_evaluation": "A",
      "level_test_team": {
        "song": "Stand Out Fit In"
      },
      "group_battle": {
        "song": "Bite Me -Japanese ver.-",
        "team": "Kiss Me",
        "result": "lose"
      }
    },
    {
      "rank": 22,
      "name_jp": "山下 柊",
      "name_romaji": "Yamashita Shu",
      "stage_name": "Y.SHU",
      "image_id": "yamashitashu",
      "rank_history": {
        "p1": 28,
        "p2": 31,
        "rc1": 34,
        "rc2": 22
      },
      "debuted": false,
      "ongoing_rank": true,
      "level_test": "C",
      "re_evaluation": "C",
      "level_test_team": {
        "song": "はじめまして"
      },
      "group_battle": {
        "song": "最高到達点",
        "team": "1peak",
        "result": "lose"
      }
    },
    {
      "rank": 23,
      "name_jp": "横山 奏夢",
      "name_romaji": "Yokoyama Kaname",
      "stage_name": "KANAME",
      "image_id": "yokoyamakaname",
      "rank_history": {
        "p1": 27,
        "p2": 26,
        "rc1": 21,
        "rc2": 23
      },
      "debuted": false,
      "ongoing_rank": true,
      "level_test": "A",
      "re_evaluation": "C",
      "level_test_team": {
        "song": "Bling-Bang-Bang-Born"
      },
      "group_battle": {
        "song": "Love Seeker",
        "team": "Full Counter",
        "result": "win"
      }
    },
    {
      "rank": 24,
      "name_jp": "イ・ヒョンジェ",
      "name_romaji": "Lee Hyunjae",
      "stage_name": "HYUNJAE",
      "image_id": "leehyunjae",
      "rank_history": {
        "p1": 21,
        "p2": 21,
        "rc1": 20,
        "rc2": 24
      },
      "debuted": false,
      "ongoing_rank": true,
      "level_test": "F",
      "re_evaluation": "C",
      "level_test_team": {
        "song": "きらり"
      },
      "group_battle": {
        "song": "Bite Me -Japanese ver.-",
        "team": "Kiss Me",
        "result": "lose"
      }
    },
    {
      "rank": 25,
      "name_jp": "ユン・ジェヨン",
      "name_romaji": "Yoon Jaeyong",
      "stage_name": "JAEYONG",
      "image_id": "yoonjaeyong",
      "rank_history": {
        "p1": 32,
        "p2": 33,
        "rc1": 33,
        "rc2": 25
      },
      "debuted": false,
      "ongoing_rank": true,
      "level_test": "D",
      "re_evaluation": "A",
      "group_battle": {
        "song": "Energetic",
        "team": "flow1",
        "result": "lose"
      }
    },
    {
      "rank": 26,
      "name_jp": "小林 千悟",
      "name_romaji": "Kobayashi Chisato",
      "stage_name": "CHISATO",
      "image_id": "kobayashichisato",
      "rank_history": {
        "p1": 23,
        "p2": 23,
        "rc1": 27,
        "rc2": 26
      },
      "debuted": false,
      "ongoing_rank": true,
      "level_test": "B",
      "re_evaluation": "B",
      "level_test_team": {
        "song": "MORE"
      },
      "group_battle": {
        "song": "LOUD",
        "team": "BE PLoud",
        "result": "lose"
      }
    },
    {
      "rank": 27,
      "name_jp": "大林 悠成",
      "name_romaji": "Obayashi Yusei",
      "stage_name": "O.YUSEI",
      "image_id": "obayashiyusei",
      "rank_history": {
        "p1": 24,
        "p2": 22,
        "rc1": 24,
        "rc2": 27
      },
      "debuted": false,
      "ongoing_rank": true,
      "level_test": "B",
      "re_evaluation": "A",
      "level_test_team": {
        "song": "第ゼロ感"
      },
      "group_battle": {
        "song": "LOUD",
        "team": "BE PLoud",
        "result": "lose"
      }
    },
    {
      "rank": 28,
      "name_jp": "倉橋 吾槙",
      "name_romaji": "Kurahashi Goten",
      "stage_name": "GOTEN",
      "image_id": "kurahashigoten",
      "rank_history": {
        "p1": 11,
        "p2": 13,
        "rc1": 11,
        "rc2": 28
      },
      "debuted": false,
      "ongoing_rank": true,
      "level_test": "B",
      "re_evaluation": "F",
      "level_test_team": {
        "song": "第ゼロ感"
      },
      "group_battle": {
        "song": "IRIS OUT",
        "team": "喜怒I6",
        "result": "win"
      }
    },
    {
      "rank": 29,
      "name_jp": "小笠原 ジュゼッペ 慧",
      "name_romaji": "Ogasawara Giuseppe Kei",
      "stage_name": "GIUSEPPE",
      "image_id": "ogasawaragiuseppekei",
      "rank_history": {
        "p1": 18,
        "p2": 20,
        "rc1": 28,
        "rc2": 29
      },
      "debuted": false,
      "ongoing_rank": true,
      "level_test": "A",
      "re_evaluation": "B",
      "level_test_team": {
        "song": "WOKE UP"
      },
      "group_battle": {
        "song": "Energetic",
        "team": "flow1",
        "result": "lose"
      }
    },
    {
      "rank": 30,
      "name_jp": "石田 亮太",
      "name_romaji": "Ishida Ryota",
      "stage_name": "RYOTA",
      "image_id": "ishidaryota",
      "rank_history": {
        "p1": 41,
        "p2": 38,
        "rc1": 38,
        "rc2": 30
      },
      "debuted": false,
      "ongoing_rank": true,
      "level_test": "B",
      "re_evaluation": "A",
      "level_test_team": {
        "song": "Cry Baby"
      },
      "group_battle": {
        "song": "LOUD",
        "team": "BE PLoud",
        "result": "lose"
      }
    },
    {
      "rank": 31,
      "name_jp": "リュウ・カイチ",
      "name_romaji": "Liu Kaichi",
      "stage_name": "KAICHI",
      "image_id": "liukaichi",
      "rank_history": {
        "p1": 68,
        "p2": 73,
        "rc1": 43,
        "rc2": 31
      },
      "debuted": false,
      "ongoing_rank": true,
      "level_test": "F",
      "re_evaluation": "F",
      "level_test_team": {
        "song": "Paradise"
      },
      "group_battle": {
        "song": "Love Seeker",
        "team": "Heart Shakers",
        "result": "lose"
      }
    },
    {
      "rank": 32,
      "name_jp": "岡田 侑磨",
      "name_romaji": "Okada Yuma",
      "stage_name": "YUMA",
      "image_id": "okadayuma",
      "rank_history": {
        "p1": 47,
        "p2": 48,
        "rc1": 39,
        "rc2": 32
      },
      "debuted": false,
      "ongoing_rank": true,
      "level_test": "D",
      "re_evaluation": "D",
      "level_test_team": {
        "song": "はじめまして"
      },
      "group_battle": {
        "song": "Bite Me -Japanese ver.-",
        "team": "Kiss Me",
        "result": "lose"
      }
    },
    {
      "rank": 33,
      "name_jp": "篠ヶ谷 歩夢",
      "name_romaji": "Shinogaya Ayumu",
      "stage_name": "S.AYUMU",
      "image_id": "shinogayaayumu",
      "rank_history": {
        "p1": 29,
        "p2": 30,
        "rc1": 32,
        "rc2": 33
      },
      "debuted": false,
      "ongoing_rank": true,
      "level_test": "C",
      "re_evaluation": "B",
      "level_test_team": {
        "song": "Rocketeer"
      },
      "group_battle": {
        "song": "LOUD",
        "team": "BE PLoud",
        "result": "lose"
      }
    },
    {
      "rank": 34,
      "name_jp": "田中 蒔",
      "name_romaji": "Tanaka Maki",
      "stage_name": "MAKI",
      "image_id": "tanakamaki",
      "rank_history": {
        "p1": 25,
        "p2": 29,
        "rc1": 30,
        "rc2": 34
      },
      "debuted": false,
      "ongoing_rank": true,
      "level_test": "D",
      "re_evaluation": "F",
      "level_test_team": {
        "song": "踊り子"
      },
      "group_battle": {
        "song": "IRIS OUT",
        "team": "喜怒I6",
        "result": "win"
      }
    },
    {
      "rank": 35,
      "name_jp": "今江 陸斗",
      "name_romaji": "Imae Rikuto",
      "stage_name": "I.RIKUTO",
      "image_id": "imaerikuto",
      "rank_history": {
        "p1": 35,
        "p2": 36,
        "rc1": 31,
        "rc2": 35
      },
      "debuted": false,
      "ongoing_rank": true,
      "level_test": "B",
      "re_evaluation": "D",
      "level_test_team": {
        "song": "SEVENTEEN"
      },
      "group_battle": {
        "song": "Bite Me -Japanese ver.-",
        "team": "虹色Bites",
        "result": "win"
      }
    },
    {
      "rank": 36,
      "name_jp": "アーチャー・ウイ",
      "name_romaji": "Archer Uy",
      "stage_name": "ARCHER",
      "image_id": "archeruy",
      "rank_history": {
        "p1": 20,
        "p2": 18,
        "rc1": 22,
        "rc2": 36
      },
      "debuted": false,
      "ongoing_rank": true,
      "level_test": "B",
      "re_evaluation": "B",
      "level_test_team": {
        "song": "両片想い"
      },
      "group_battle": {
        "song": "唱",
        "team": "GLOBOYS",
        "result": "lose"
      }
    },
    {
      "rank": 37,
      "name_jp": "松田 太雅",
      "name_romaji": "Matsuda Taiga",
      "stage_name": "M.TAIGA",
      "image_id": "matsudataiga",
      "rank_history": {
        "p1": 30,
        "p2": 32,
        "rc1": 35,
        "rc2": 37
      },
      "debuted": false,
      "ongoing_rank": true,
      "level_test": "C",
      "re_evaluation": "D",
      "level_test_team": {
        "song": "SHINE (Japanese ver.)"
      },
      "group_battle": {
        "song": "Energetic",
        "team": "TO BE ENERGY",
        "result": "win"
      }
    },
    {
      "rank": 38,
      "name_jp": "板倉 悠太",
      "name_romaji": "Itakura Yuta",
      "stage_name": "YUTA",
      "image_id": "itakurayuta",
      "rank_history": {
        "p1": 19,
        "p2": 19,
        "rc1": 29,
        "rc2": 38
      },
      "debuted": false,
      "ongoing_rank": true,
      "level_test": "B",
      "re_evaluation": "F",
      "level_test_team": {
        "song": "Stand Out Fit In"
      },
      "group_battle": {
        "song": "最高到達点",
        "team": "新世海マリーンズ",
        "result": "win"
      }
    },
    {
      "rank": 39,
      "name_jp": "カク・ドンミン",
      "name_romaji": "Kwak Dongmin",
      "stage_name": "DONGMIN",
      "image_id": "kwakdongmin",
      "rank_history": {
        "p1": 33,
        "p2": 35,
        "rc1": 37,
        "rc2": 39
      },
      "debuted": false,
      "ongoing_rank": true,
      "level_test": "D",
      "re_evaluation": "B",
      "level_test_team": {
        "song": "My Way"
      },
      "group_battle": {
        "song": "LOUD",
        "team": "BE PLoud",
        "result": "lose"
      }
    },
    {
      "rank": 40,
      "name_jp": "リー・ウェイゼ",
      "name_romaji": "Li Weize",
      "stage_name": "WEIZE",
      "image_id": "liweize",
      "rank_history": {
        "p1": 53,
        "p2": 54,
        "rc1": 44,
        "rc2": 40
      },
      "debuted": false,
      "ongoing_rank": true,
      "level_test": "B",
      "re_evaluation": "D",
      "level_test_team": {
        "song": "Paradise"
      },
      "group_battle": {
        "song": "Bite Me -Japanese ver.-",
        "team": "虹色Bites",
        "result": "win"
      }
    },
    {
      "rank": 41,
      "name_jp": "西﨑 柊",
      "name_romaji": "Nishizaki Shu",
      "stage_name": "N.SHU",
      "image_id": "nishizakishu",
      "rank_history": {
        "p1": 45,
        "p2": 44,
        "rc1": 49,
        "rc2": 41
      },
      "debuted": false,
      "ongoing_rank": true,
      "level_test": "D",
      "re_evaluation": "F",
      "level_test_team": {
        "song": "トリコ"
      },
      "group_battle": {
        "song": "LOUD",
        "team": "BE PLoud",
        "result": "lose"
      }
    },
    {
      "rank": 42,
      "name_jp": "藤牧 大雅",
      "name_romaji": "Fujimaki Taiga",
      "stage_name": "F.TAIGA",
      "image_id": "fujimakitaiga",
      "rank_history": {
        "p1": 34,
        "p2": 34,
        "rc1": 36,
        "rc2": 42
      },
      "debuted": false,
      "ongoing_rank": true,
      "level_test": "B",
      "re_evaluation": "A",
      "level_test_team": {
        "song": "Back to Life"
      },
      "group_battle": {
        "song": "Bite Me -Japanese ver.-",
        "team": "Kiss Me",
        "result": "lose"
      }
    },
    {
      "rank": 43,
      "name_jp": "ジュアン・ジェイ",
      "name_romaji": "Chuang Jay",
      "stage_name": "JAY",
      "image_id": "chuangjay",
      "rank_history": {
        "p1": 50,
        "p2": 45,
        "rc1": 47,
        "rc2": 43
      },
      "debuted": false,
      "ongoing_rank": true,
      "level_test": "C",
      "re_evaluation": "B",
      "level_test_team": {
        "song": "Don't Tell Nobody"
      },
      "group_battle": {
        "song": "唱",
        "team": "GLOBOYS",
        "result": "lose"
      }
    },
    {
      "rank": 44,
      "name_jp": "金安 純正",
      "name_romaji": "Kaneyasu Junsei",
      "stage_name": "JUNSEI",
      "image_id": "kaneyasujunsei",
      "rank_history": {
        "p1": 40,
        "p2": 43,
        "rc1": 50,
        "rc2": 44
      },
      "debuted": false,
      "ongoing_rank": true,
      "level_test": "C",
      "re_evaluation": "D",
      "level_test_team": {
        "song": "Rocketeer"
      },
      "group_battle": {
        "song": "Bite Me -Japanese ver.-",
        "team": "虹色Bites",
        "result": "win"
      }
    },
    {
      "rank": 45,
      "name_jp": "宇野 海夢",
      "name_romaji": "Uno Kaimu",
      "stage_name": "KAIMU",
      "image_id": "unokaimu",
      "rank_history": {
        "p1": 42,
        "p2": 42,
        "rc1": 48,
        "rc2": 45
      },
      "debuted": false,
      "ongoing_rank": true,
      "level_test": "C",
      "re_evaluation": "D",
      "level_test_team": {
        "song": "Goosebumps"
      },
      "group_battle": {
        "song": "最高到達点",
        "team": "1peak",
        "result": "lose"
      }
    },
    {
      "rank": 46,
      "name_jp": "大瀬 凜和",
      "name_romaji": "Ohse Rinto",
      "stage_name": "RINTO",
      "image_id": "ohserinto",
      "rank_history": {
        "p1": 46,
        "p2": 46,
        "rc1": 46,
        "rc2": 46
      },
      "debuted": false,
      "ongoing_rank": true,
      "level_test": "A",
      "re_evaluation": "C",
      "level_test_team": {
        "song": "イケナイ太陽"
      },
      "group_battle": {
        "song": "Love Seeker",
        "team": "Heart Shakers",
        "result": "lose"
      }
    },
    {
      "rank": 47,
      "name_jp": "澤井 星名",
      "name_romaji": "Sawai Sena",
      "stage_name": "SENA",
      "image_id": "sawaisena",
      "rank_history": {
        "p1": 36,
        "p2": 40,
        "rc1": 40,
        "rc2": 47
      },
      "debuted": false,
      "ongoing_rank": true,
      "level_test": "D",
      "re_evaluation": "D",
      "level_test_team": {
        "song": "SHINE (Japanese ver.)"
      }
    },
    {
      "rank": 48,
      "name_jp": "南平 達矢",
      "name_romaji": "Minamihira Tatsuya",
      "stage_name": "TATSUYA",
      "image_id": "minamihiratatsuya",
      "rank_history": {
        "p1": 43,
        "p2": 47,
        "rc1": 41,
        "rc2": 48
      },
      "debuted": false,
      "ongoing_rank": true,
      "level_test": "C",
      "re_evaluation": "C",
      "level_test_team": {
        "song": "Share The World"
      }
    },
    {
      "rank": 49,
      "name_jp": "髙橋 空良",
      "name_romaji": "Takahashi Sora",
      "stage_name": "T.SORA",
      "image_id": "takahashisora",
      "rank_history": {
        "p1": 37,
        "p2": 39,
        "rc1": 42,
        "rc2": 49
      },
      "debuted": false,
      "ongoing_rank": true,
      "level_test": "F",
      "re_evaluation": "F",
      "level_test_team": {
        "song": "WISH (Japanese ver.)"
      },
      "group_battle": {
        "song": "Love Seeker",
        "team": "Heart Shakers",
        "result": "lose"
      }
    },
    {
      "rank": 50,
      "name_jp": "森 明育",
      "name_romaji": "Mori Mei",
      "stage_name": "MEI",
      "image_id": "morimei",
      "rank_history": {
        "p1": 39,
        "p2": 41,
        "rc1": 45,
        "rc2": 50
      },
      "debuted": false,
      "ongoing_rank": true,
      "level_test": "F",
      "re_evaluation": "F",
      "level_test_team": {
        "song": "いいじゃん"
      }
    },
    {
      "rank": null,
      "name_jp": "中丸 晏寿",
      "name_romaji": "Nakamaru Aju",
      "stage_name": "AJU",
      "image_id": "nakamaruaju",
      "rank_history": {
        "p1": 54,
        "p2": 57,
        "rc1": 64
      },
      "debuted": false,
      "ongoing_rank": false,
      "level_test": "D",
      "re_evaluation": "B",
      "level_test_team": {
        "song": "RadioVision"
      },
      "group_battle": {
        "song": "IRIS OUT",
        "team": "喜怒I6",
        "result": "win"
      }
    },
    {
      "rank": null,
      "name_jp": "本荘 晃",
      "name_romaji": "Honjo Akira",
      "stage_name": "AKIRA",
      "image_id": "honjoakira",
      "rank_history": {
        "p1": 51,
        "p2": 52,
        "rc1": 56
      },
      "debuted": false,
      "ongoing_rank": false,
      "level_test": "F",
      "re_evaluation": "B",
      "level_test_team": {
        "song": "Butter-Fly"
      },
      "group_battle": {
        "song": "Love Seeker",
        "team": "Full Counter",
        "result": "win"
      }
    },
    {
      "rank": null,
      "name_jp": "オム・スアンカワーテン",
      "name_romaji": "Aom Suungkavathin",
      "stage_name": "AOM",
      "image_id": "aomsuungkavathin",
      "rank_history": {
        "p1": 67,
        "p2": 72,
        "rc1": 81
      },
      "debuted": false,
      "ongoing_rank": false,
      "level_test": "D",
      "re_evaluation": "C",
      "level_test_team": {
        "song": "WOKE UP"
      },
      "group_battle": {
        "song": "Love Seeker",
        "team": "Full Counter",
        "result": "win"
      }
    },
    {
      "rank": null,
      "name_jp": "児島 歩夢",
      "name_romaji": "Kojima Ayumu",
      "stage_name": "K.AYUMU",
      "image_id": "kojimaayumu",
      "rank_history": {
        "p1": 75,
        "p2": 83,
        "rc1": 94
      },
      "debuted": false,
      "ongoing_rank": false,
      "level_test": "F",
      "re_evaluation": "B",
      "level_test_team": {
        "song": "I Wonder"
      },
      "group_battle": {
        "song": "最高到達点",
        "team": "1peak",
        "result": "lose"
      }
    },
    {
      "rank": null,
      "name_jp": "市川 大輝",
      "name_romaji": "Ichikawa Daiki",
      "stage_name": "I.DAIKI",
      "image_id": "ichikawadaiki",
      "rank_history": {
        "p1": 66,
        "p2": 62,
        "rc1": 66
      },
      "debuted": false,
      "ongoing_rank": false,
      "level_test": "F",
      "re_evaluation": "D",
      "level_test_team": {
        "song": "WOKE UP"
      },
      "group_battle": {
        "song": "最高到達点",
        "team": "新世海マリーンズ",
        "result": "win"
      }
    },
    {
      "rank": null,
      "name_jp": "末川 瑛太",
      "name_romaji": "Suekawa Eita",
      "stage_name": "EITA",
      "image_id": "suekawaeita",
      "rank_history": {
        "p1": 83,
        "p2": 79,
        "rc1": 89
      },
      "debuted": false,
      "ongoing_rank": false,
      "level_test": "C",
      "re_evaluation": "C",
      "level_test_team": {
        "song": "RadioVision"
      },
      "group_battle": {
        "song": "LOUD",
        "team": "フレフレラウダーズ",
        "result": "win"
      }
    },
    {
      "rank": null,
      "name_jp": "金田 栄都",
      "name_romaji": "Kaneda Eito",
      "stage_name": "K.EITO",
      "image_id": "kanedaeito",
      "rank_history": {
        "p1": 52,
        "p2": 53,
        "rc1": 57
      },
      "debuted": false,
      "ongoing_rank": false,
      "level_test": "D",
      "re_evaluation": "D",
      "level_test_team": {
        "song": "Back to Life"
      },
      "group_battle": {
        "song": "IRIS OUT",
        "team": "CREEEPY DEVILS",
        "result": "lose"
      }
    },
    {
      "rank": null,
      "name_jp": "櫻井 楓真",
      "name_romaji": "Sakurai Fuma",
      "stage_name": "FUMA",
      "image_id": "sakuraifuma",
      "rank_history": {
        "p1": 59,
        "p2": 59,
        "rc1": 62
      },
      "debuted": false,
      "ongoing_rank": false,
      "level_test": "D",
      "re_evaluation": "C",
      "level_test_team": {
        "song": "RadioVision"
      },
      "group_battle": {
        "song": "Energetic",
        "team": "TO BE ENERGY",
        "result": "win"
      }
    },
    {
      "rank": null,
      "name_jp": "村松 遼空",
      "name_romaji": "Muramatsu Haruku",
      "stage_name": "HARUKU",
      "image_id": "muramatsuharuku",
      "rank_history": {
        "p1": 74,
        "p2": 78,
        "rc1": 87
      },
      "debuted": false,
      "ongoing_rank": false,
      "level_test": "F",
      "re_evaluation": "F",
      "level_test_team": {
        "song": "Butter-Fly"
      },
      "group_battle": {
        "song": "LOUD",
        "team": "フレフレラウダーズ",
        "result": "win"
      }
    },
    {
      "rank": null,
      "name_jp": "髙城 暖人",
      "name_romaji": "Takagi Haruto",
      "stage_name": "HARUTO",
      "image_id": "takagiharuto",
      "rank_history": {
        "p1": 58,
        "p2": 60,
        "rc1": 70
      },
      "debuted": false,
      "ongoing_rank": false,
      "level_test": "F",
      "re_evaluation": "F",
      "level_test_team": {
        "song": "いいじゃん"
      }
    },
    {
      "rank": null,
      "name_jp": "堀尾 聖",
      "name_romaji": "Horio Hijiri",
      "stage_name": "HIJIRI",
      "image_id": "horiohijiri",
      "rank_history": {
        "p1": 63,
        "p2": 63,
        "rc1": 55
      },
      "debuted": false,
      "ongoing_rank": false,
      "level_test": "C",
      "re_evaluation": "B",
      "level_test_team": {
        "song": "Cry Baby"
      },
      "group_battle": {
        "song": "Energetic",
        "team": "TO BE ENERGY",
        "result": "win"
      }
    },
    {
      "rank": null,
      "name_jp": "平島 輝",
      "name_romaji": "Hirashima Hikaru",
      "stage_name": "H.HIKARU",
      "image_id": "hirashimahikaru",
      "rank_history": {
        "p1": 44,
        "p2": 49,
        "rc1": 53
      },
      "debuted": false,
      "ongoing_rank": false,
      "level_test": "F",
      "re_evaluation": "F",
      "level_test_team": {
        "song": "今日だけI LOVE YOU (Japanese ver.)"
      },
      "group_battle": {
        "song": "LOUD",
        "team": "フレフレラウダーズ",
        "result": "win"
      }
    },
    {
      "rank": null,
      "name_jp": "瑞慶覧 太都",
      "name_romaji": "Zukeran Hiroto",
      "stage_name": "HIROTO",
      "image_id": "zukeranhiroto",
      "rank_history": {
        "p1": 71,
        "p2": 76,
        "rc1": 76
      },
      "debuted": false,
      "ongoing_rank": false,
      "level_test": "B",
      "re_evaluation": "D",
      "level_test_team": {
        "song": "イケナイ太陽"
      },
      "group_battle": {
        "song": "唱",
        "team": "GLOBOYS",
        "result": "lose"
      }
    },
    {
      "rank": null,
      "name_jp": "岡田 彪吾",
      "name_romaji": "Okada Hyugo",
      "stage_name": "HYUGO",
      "image_id": "okadahyugo",
      "rank_history": {
        "p1": 93,
        "p2": 75,
        "rc1": 77
      },
      "debuted": false,
      "ongoing_rank": false,
      "level_test": "B",
      "re_evaluation": "A",
      "level_test_team": {
        "song": "Goosebumps"
      },
      "group_battle": {
        "song": "CASE143",
        "team": "Re:TRuST",
        "result": "lose"
      }
    },
    {
      "rank": null,
      "name_jp": "丸尾 尋一郎",
      "name_romaji": "Maruo Jinichiro",
      "stage_name": "JINICHIRO",
      "image_id": "maruojinichiro",
      "rank_history": {
        "p1": 62,
        "p2": 61,
        "rc1": 52
      },
      "debuted": false,
      "ongoing_rank": false,
      "level_test": "C",
      "re_evaluation": "D",
      "level_test_team": {
        "song": "Goosebumps"
      },
      "group_battle": {
        "song": "IRIS OUT",
        "team": "喜怒I6",
        "result": "win"
      }
    },
    {
      "rank": null,
      "name_jp": "河邊 晟",
      "name_romaji": "Kawabe Joe",
      "stage_name": "JOE",
      "image_id": "kawabejoe",
      "rank_history": {
        "p1": 101,
        "p2": 91,
        "rc1": 99
      },
      "debuted": false,
      "ongoing_rank": false,
      "level_test": "D",
      "re_evaluation": "D",
      "level_test_team": {
        "song": "トリコ"
      },
      "group_battle": {
        "song": "Love Seeker",
        "team": "Heart Shakers",
        "result": "lose"
      }
    },
    {
      "rank": null,
      "name_jp": "シン・ジョンウク",
      "name_romaji": "Shin Junguk",
      "stage_name": "JUNGUK",
      "image_id": "shinjunguk",
      "rank_history": {
        "p1": 87,
        "p2": 101,
        "rc1": 93
      },
      "debuted": false,
      "ongoing_rank": false,
      "level_test": "C",
      "re_evaluation": "C",
      "level_test_team": {
        "song": "きらり"
      },
      "group_battle": {
        "song": "唱",
        "team": "GLOBOYS",
        "result": "lose"
      }
    },
    {
      "rank": null,
      "name_jp": "多比 奏聖",
      "name_romaji": "Tabi Kanade",
      "stage_name": "KANADE",
      "image_id": "tabikanade",
      "rank_history": {
        "p1": 99,
        "p2": 93,
        "rc1": 85
      },
      "debuted": false,
      "ongoing_rank": false,
      "level_test": "A",
      "re_evaluation": "B",
      "level_test_team": {
        "song": "トリコ"
      },
      "group_battle": {
        "song": "Love Seeker",
        "team": "Heart Shakers",
        "result": "lose"
      }
    },
    {
      "rank": null,
      "name_jp": "黒﨑 貫汰",
      "name_romaji": "Kurosaki Kanta",
      "stage_name": "KANTA",
      "image_id": "kurosakikanta",
      "rank_history": {
        "p1": 57,
        "p2": 56,
        "rc1": 69
      },
      "debuted": false,
      "ongoing_rank": false,
      "level_test": "F",
      "re_evaluation": "D",
      "level_test_team": {
        "song": "イケナイ太陽"
      },
      "group_battle": {
        "song": "CASE143",
        "team": "上等Kids(♡)",
        "result": "win"
      }
    },
    {
      "rank": null,
      "name_jp": "関 敬次郎",
      "name_romaji": "Seki Keijiro",
      "stage_name": "KEIJIRO",
      "image_id": "sekikeijiro",
      "rank_history": {
        "p1": 98,
        "p2": 98,
        "rc1": 94
      },
      "debuted": false,
      "ongoing_rank": false,
      "level_test": "C",
      "re_evaluation": "B",
      "level_test_team": {
        "song": "Cry Baby"
      },
      "group_battle": {
        "song": "最高到達点",
        "team": "1peak",
        "result": "lose"
      }
    },
    {
      "rank": null,
      "name_jp": "黄 敬眞",
      "name_romaji": "Ko Keishin",
      "stage_name": "KEISHIN",
      "image_id": "kokeishin",
      "rank_history": {
        "p1": 69,
        "p2": 74,
        "rc1": 88
      },
      "debuted": false,
      "ongoing_rank": false,
      "level_test": "F",
      "re_evaluation": "F",
      "level_test_team": {
        "song": "トリコ"
      },
      "group_battle": {
        "song": "LOUD",
        "team": "フレフレラウダーズ",
        "result": "win"
      }
    },
    {
      "rank": null,
      "name_jp": "髙松 敬祐",
      "name_romaji": "Takamatsu Keisuke",
      "stage_name": "KEISUKE",
      "image_id": "takamatsukeisuke",
      "rank_history": {
        "p1": 90,
        "p2": 96,
        "rc1": 100
      },
      "debuted": false,
      "ongoing_rank": false,
      "level_test": "C",
      "re_evaluation": "F",
      "level_test_team": {
        "song": "第ゼロ感"
      },
      "group_battle": {
        "song": "CASE143",
        "team": "上等Kids(♡)",
        "result": "win"
      }
    },
    {
      "rank": null,
      "name_jp": "西山 賢人",
      "name_romaji": "Nishiyama Kento",
      "stage_name": "KENTO",
      "image_id": "nishiyamakento",
      "rank_history": {
        "p1": 96,
        "p2": 99,
        "rc1": 92
      },
      "debuted": false,
      "ongoing_rank": false,
      "level_test": "C",
      "re_evaluation": "D",
      "level_test_team": {
        "song": "Share The World"
      },
      "group_battle": {
        "song": "Love Seeker",
        "team": "Full Counter",
        "result": "win"
      }
    },
    {
      "rank": null,
      "name_jp": "河合 晃誠",
      "name_romaji": "Kawai Kosei",
      "stage_name": "KOSEI",
      "image_id": "kawaikosei",
      "rank_history": {
        "p1": 94,
        "p2": 87,
        "rc1": 75
      },
      "debuted": false,
      "ongoing_rank": false,
      "level_test": "D",
      "re_evaluation": "D",
      "level_test_team": {
        "song": "MORE"
      },
      "group_battle": {
        "song": "Bite Me -Japanese ver.-",
        "team": "虹色Bites",
        "result": "win"
      }
    },
    {
      "rank": null,
      "name_jp": "髙谷 京平",
      "name_romaji": "Takaya Kyohei",
      "stage_name": "KYOHEI",
      "image_id": "takayakyohei",
      "rank_history": {
        "p1": 86,
        "p2": 86,
        "rc1": 59
      },
      "debuted": false,
      "ongoing_rank": false,
      "level_test": "C",
      "re_evaluation": "F",
      "level_test_team": {
        "song": "Bling-Bang-Bang-Born"
      },
      "group_battle": {
        "song": "IRIS OUT",
        "team": "喜怒I6",
        "result": "win"
      }
    },
    {
      "rank": null,
      "name_jp": "山根 武蔵",
      "name_romaji": "Yamane Musashi",
      "stage_name": "MUSASHI",
      "image_id": "yamanemusashi",
      "rank_history": {
        "p1": 65,
        "p2": 68,
        "rc1": 79
      },
      "debuted": false,
      "ongoing_rank": false,
      "level_test": "D",
      "re_evaluation": "D",
      "level_test_team": {
        "song": "My Way"
      },
      "group_battle": {
        "song": "CASE143",
        "team": "Re:TRuST",
        "result": "lose"
      }
    },
    {
      "rank": null,
      "name_jp": "堀野 蓮",
      "name_romaji": "Horino Ren",
      "stage_name": "H.REN",
      "image_id": "horinoren",
      "rank_history": {
        "p1": 56,
        "p2": 50,
        "rc1": 51
      },
      "debuted": false,
      "ongoing_rank": false,
      "level_test": "B",
      "re_evaluation": "C",
      "level_test_team": {
        "song": "Supercali"
      },
      "group_battle": {
        "song": "LOUD",
        "team": "BE PLoud",
        "result": "lose"
      }
    },
    {
      "rank": null,
      "name_jp": "小林 蓮翔",
      "name_romaji": "Kobayashi Rento",
      "stage_name": "K.RENTO",
      "image_id": "kobayashirento",
      "rank_history": {
        "p1": 55,
        "p2": 58,
        "rc1": 80
      },
      "debuted": false,
      "ongoing_rank": false,
      "level_test": "F",
      "re_evaluation": "F",
      "level_test_team": {
        "song": "はじめまして"
      },
      "group_battle": {
        "song": "CASE143",
        "team": "Re:TRuST",
        "result": "lose"
      }
    },
    {
      "rank": null,
      "name_jp": "神元 理丘",
      "name_romaji": "Kamimoto Riku",
      "stage_name": "RIKU",
      "image_id": "kamimotoriku",
      "rank_history": {
        "p1": 97,
        "p2": 71,
        "rc1": 65
      },
      "debuted": false,
      "ongoing_rank": false,
      "level_test": "A",
      "re_evaluation": "A",
      "level_test_team": {
        "song": "I Wonder"
      },
      "group_battle": {
        "song": "Bite Me -Japanese ver.-",
        "team": "Kiss Me",
        "result": "lose"
      }
    },
    {
      "rank": null,
      "name_jp": "鳩場 陸人",
      "name_romaji": "Hatoba Rikuto",
      "stage_name": "H.RIKUTO",
      "image_id": "hatobarikuto",
      "rank_history": {
        "p1": 84,
        "p2": 88,
        "rc1": 97
      },
      "debuted": false,
      "ongoing_rank": false,
      "level_test": "B",
      "re_evaluation": "B",
      "level_test_team": {
        "song": "Gooey"
      },
      "group_battle": {
        "song": "CASE143",
        "team": "上等Kids(♡)",
        "result": "win"
      }
    },
    {
      "rank": null,
      "name_jp": "甲斐 陸也",
      "name_romaji": "Kai Rikuya",
      "stage_name": "RIKUYA",
      "image_id": "kairikuya",
      "rank_history": {
        "p1": 88,
        "p2": 97,
        "rc1": 98
      },
      "debuted": false,
      "ongoing_rank": false,
      "level_test": "B",
      "re_evaluation": "C",
      "level_test_team": {
        "song": "MORE"
      },
      "group_battle": {
        "song": "CASE143",
        "team": "Re:TRuST",
        "result": "lose"
      }
    },
    {
      "rank": null,
      "name_jp": "水上 琉偉",
      "name_romaji": "Mizugami Rui",
      "stage_name": "M.RUI",
      "image_id": "mizugamirui",
      "rank_history": {
        "p1": 61,
        "p2": 64,
        "rc1": 72
      },
      "debuted": false,
      "ongoing_rank": false,
      "level_test": "F",
      "re_evaluation": "F",
      "level_test_team": {
        "song": "Butter-Fly"
      },
      "group_battle": {
        "song": "Love Seeker",
        "team": "Full Counter",
        "result": "win"
      }
    },
    {
      "rank": null,
      "name_jp": "上野 琉偉",
      "name_romaji": "Ueno Rui",
      "stage_name": "U.RUI",
      "image_id": "uenorui",
      "rank_history": {
        "p1": 79,
        "p2": 100,
        "rc1": 101
      },
      "debuted": false,
      "ongoing_rank": false,
      "level_test": "C",
      "re_evaluation": "C",
      "level_test_team": {
        "song": "今日だけI LOVE YOU (Japanese ver.)"
      },
      "group_battle": {
        "song": "CASE143",
        "team": "Re:TRuST",
        "result": "lose"
      }
    },
    {
      "rank": null,
      "name_jp": "岡戸 竜芽",
      "name_romaji": "Okado Ryuga",
      "stage_name": "RYUGA",
      "image_id": "okadoryuga",
      "rank_history": {
        "p1": 95,
        "p2": 84,
        "rc1": 91
      },
      "debuted": false,
      "ongoing_rank": false,
      "level_test": "A",
      "re_evaluation": "C",
      "level_test_team": {
        "song": "Goosebumps"
      },
      "group_battle": {
        "song": "最高到達点",
        "team": "1peak",
        "result": "lose"
      }
    },
    {
      "rank": null,
      "name_jp": "香月 誠太",
      "name_romaji": "Katsuki Seita",
      "stage_name": "SEITA",
      "image_id": "katsukiseita",
      "rank_history": {
        "p1": 91,
        "p2": 67,
        "rc1": 71
      },
      "debuted": false,
      "ongoing_rank": false,
      "level_test": "A",
      "re_evaluation": "B",
      "level_test_team": {
        "song": "Don't Tell Nobody"
      },
      "group_battle": {
        "song": "最高到達点",
        "team": "1peak",
        "result": "lose"
      }
    },
    {
      "rank": null,
      "name_jp": "岩城 慎二",
      "name_romaji": "Iwaki Shinji",
      "stage_name": "SHINJI",
      "image_id": "iwakishinji",
      "rank_history": {
        "p1": 73,
        "p2": 66,
        "rc1": 60
      },
      "debuted": false,
      "ongoing_rank": false,
      "level_test": "B",
      "re_evaluation": "A",
      "level_test_team": {
        "song": "Rocketeer"
      },
      "group_battle": {
        "song": "IRIS OUT",
        "team": "CREEEPY DEVILS",
        "result": "lose"
      }
    },
    {
      "rank": null,
      "name_jp": "宮崎 真佑",
      "name_romaji": "Miyazaki Shinsuke",
      "stage_name": "SHINSUKE",
      "image_id": "miyazakishinsuke",
      "rank_history": {
        "p1": 72,
        "p2": 77,
        "rc1": 86
      },
      "debuted": false,
      "ongoing_rank": false,
      "level_test": "B",
      "re_evaluation": "D",
      "level_test_team": {
        "song": "Gooey"
      },
      "group_battle": {
        "song": "LOUD",
        "team": "フレフレラウダーズ",
        "result": "win"
      }
    },
    {
      "rank": null,
      "name_jp": "松田 颯吾",
      "name_romaji": "Matsuda Sogo",
      "stage_name": "SOGO",
      "image_id": "matsudasogo",
      "rank_history": {
        "p1": 85,
        "p2": 81,
        "rc1": 84
      },
      "debuted": false,
      "ongoing_rank": false,
      "level_test": "F",
      "re_evaluation": "C",
      "level_test_team": {
        "song": "踊り子"
      },
      "group_battle": {
        "song": "IRIS OUT",
        "team": "CREEEPY DEVILS",
        "result": "lose"
      }
    },
    {
      "rank": null,
      "name_jp": "佐藤 碧空",
      "name_romaji": "Sato Sora",
      "stage_name": "S.SORA",
      "image_id": "satosora",
      "rank_history": {
        "p1": 77,
        "p2": 82,
        "rc1": 61
      },
      "debuted": false,
      "ongoing_rank": false,
      "level_test": "D",
      "re_evaluation": "C",
      "level_test_team": {
        "song": "Butter-Fly"
      },
      "group_battle": {
        "song": "IRIS OUT",
        "team": "喜怒I6",
        "result": "win"
      }
    },
    {
      "rank": null,
      "name_jp": "西田 颯梓",
      "name_romaji": "Nishida Soshi",
      "stage_name": "SOSHI",
      "image_id": "nishidasoshi",
      "rank_history": {
        "p1": 64,
        "p2": 65,
        "rc1": 67
      },
      "debuted": false,
      "ongoing_rank": false,
      "level_test": "F",
      "re_evaluation": "F",
      "level_test_team": {
        "song": "感電"
      },
      "group_battle": {
        "song": "Love Seeker",
        "team": "Full Counter",
        "result": "win"
      }
    },
    {
      "rank": null,
      "name_jp": "東野 蒼汰",
      "name_romaji": "Tono Sota",
      "stage_name": "SOTA",
      "image_id": "tonosota",
      "rank_history": {
        "p1": 82,
        "p2": 85,
        "rc1": 83
      },
      "debuted": false,
      "ongoing_rank": false,
      "level_test": "C",
      "re_evaluation": "B",
      "level_test_team": {
        "song": "Share The World"
      },
      "group_battle": {
        "song": "CASE143",
        "team": "上等Kids(♡)",
        "result": "win"
      }
    },
    {
      "rank": null,
      "name_jp": "金倉 拓未",
      "name_romaji": "Kanakura Takumi",
      "stage_name": "TAKUMI",
      "image_id": "kanakuratakumi",
      "rank_history": {
        "p1": 81,
        "p2": 92,
        "rc1": 90
      },
      "debuted": false,
      "ongoing_rank": false,
      "level_test": "C",
      "re_evaluation": "B",
      "level_test_team": {
        "song": "Be Alive"
      },
      "group_battle": {
        "song": "CASE143",
        "team": "上等Kids(♡)",
        "result": "win"
      }
    },
    {
      "rank": null,
      "name_jp": "宮里 拓利",
      "name_romaji": "Miyazato Takuto",
      "stage_name": "M.TAKUTO",
      "image_id": "miyazatotakuto",
      "rank_history": {
        "p1": 80,
        "p2": 95,
        "rc1": 63
      },
      "debuted": false,
      "ongoing_rank": false,
      "level_test": "C",
      "re_evaluation": "C",
      "level_test_team": {
        "song": "今日だけI LOVE YOU (Japanese ver.)"
      },
      "group_battle": {
        "song": "Love Seeker",
        "team": "Full Counter",
        "result": "win"
      }
    },
    {
      "rank": null,
      "name_jp": "岡本 拓士",
      "name_romaji": "Okamoto Takuto",
      "stage_name": "O.TAKUTO",
      "image_id": "okamototakuto",
      "rank_history": {
        "p1": 49,
        "p2": 51,
        "rc1": 58
      },
      "debuted": false,
      "ongoing_rank": false,
      "level_test": "F",
      "re_evaluation": "F",
      "level_test_team": {
        "song": "WOKE UP"
      },
      "group_battle": {
        "song": "LOUD",
        "team": "フレフレラウダーズ",
        "result": "win"
      }
    },
    {
      "rank": null,
      "name_jp": "森井 輝",
      "name_romaji": "Morii Teru",
      "stage_name": "TERU",
      "image_id": "moriiteru",
      "rank_history": {
        "p1": 100,
        "p2": 89,
        "rc1": 96
      },
      "debuted": false,
      "ongoing_rank": false,
      "level_test": "A",
      "re_evaluation": "C",
      "level_test_team": {
        "song": "Goosebumps"
      },
      "group_battle": {
        "song": "CASE143",
        "team": "Re:TRuST",
        "result": "lose"
      }
    },
    {
      "rank": null,
      "name_jp": "北林 天虎",
      "name_romaji": "Kitabayashi Tetora",
      "stage_name": "TETORA",
      "image_id": "kitabayashitetora",
      "rank_history": {
        "p1": 89,
        "p2": 94,
        "rc1": 82
      },
      "debuted": false,
      "ongoing_rank": false,
      "level_test": "D",
      "re_evaluation": "D",
      "level_test_team": {
        "song": "Share The World"
      }
    },
    {
      "rank": null,
      "name_jp": "藤芳 辰弥",
      "name_romaji": "Fujiyoshi Tokiya",
      "stage_name": "TOKIYA",
      "image_id": "fujiyoshitokiya",
      "rank_history": {
        "p1": 92,
        "p2": 90,
        "rc1": 78
      },
      "debuted": false,
      "ongoing_rank": false,
      "level_test": "F",
      "re_evaluation": "B",
      "level_test_team": {
        "song": "今日だけI LOVE YOU (Japanese ver.)"
      },
      "group_battle": {
        "song": "IRIS OUT",
        "team": "CREEEPY DEVILS",
        "result": "lose"
      }
    },
    {
      "rank": null,
      "name_jp": "増田 倫希",
      "name_romaji": "Masuda Tomoki",
      "stage_name": "TOMOKI",
      "image_id": "masudatomoki",
      "rank_history": {
        "p1": 76,
        "p2": 80,
        "rc1": 73
      },
      "debuted": false,
      "ongoing_rank": false,
      "level_test": "B",
      "re_evaluation": "F",
      "level_test_team": {
        "song": "はじめまして"
      },
      "group_battle": {
        "song": "最高到達点",
        "team": "新世海マリーンズ",
        "result": "win"
      }
    },
    {
      "rank": null,
      "name_jp": "アギナルド・トリスタン・ジェームス",
      "name_romaji": "Aguinaldo Tristan James",
      "stage_name": "TRISTAN",
      "image_id": "aguinaldotristanjames",
      "rank_history": {
        "p1": 70,
        "p2": 69,
        "rc1": 74
      },
      "debuted": false,
      "ongoing_rank": false,
      "level_test": "C",
      "re_evaluation": "F",
      "level_test_team": {
        "song": "My Way"
      },
      "group_battle": {
        "song": "IRIS OUT",
        "team": "CREEEPY DEVILS",
        "result": "lose"
      }
    },
    {
      "rank": null,
      "name_jp": "ヨハン・エマニュエル",
      "name_romaji": "Yohan Emmanuel",
      "stage_name": "YOHAN",
      "image_id": "yohanemmanuel",
      "rank_history": {
        "p1": 78,
        "p2": 70,
        "rc1": 54
      },
      "debuted": false,
      "ongoing_rank": false,
      "level_test": "D",
      "re_evaluation": "F",
      "level_test_team": {
        "song": "WOKE UP"
      },
      "group_battle": {
        "song": "唱",
        "team": "GLOBOYS",
        "result": "lose"
      }
    },
    {
      "rank": null,
      "name_jp": "佐野 由征",
      "name_romaji": "Sano Yusei",
      "stage_name": "S.YUSEI",
      "image_id": "sanoyusei",
      "rank_history": {
        "p1": 60,
        "p2": 55,
        "rc1": 68
      },
      "debuted": false,
      "ongoing_rank": false,
      "level_test": "B",
      "re_evaluation": "C",
      "level_test_team": {
        "song": "WISH (Japanese ver.)"
      },
      "group_battle": {
        "song": "LOUD",
        "team": "フレフレラウダーズ",
        "result": "win"
      }
    }
  ]
}